DEV_KIT/KIT_FIRST.py
DEV_KIT/__init__.py
DVL_KIT-0.0.3.dist-info/LICENSE.txt
DVL_KIT-0.0.3.dist-info/METADATA
DVL_KIT-0.0.3.dist-info/WHEEL
DVL_KIT-0.0.3.dist-info/top_level.txt
DVL_KIT-0.0.3.dist-info/RECORD
