Metadata-Version: 2.1
Name: DVL-KIT
Version: 0.0.3
Summary: DEV's kit
Home-page: https://github.com/Aqouthe
Author: Aqouthe
Author-email: hoonie0929@gmail.com
License: UNKNOWN
Platform: UNKNOWN
Classifier: Programming Language :: Python :: 3
Classifier: License :: OSI Approved :: MIT License
Classifier: Operating System :: OS Independent
Requires-Python: >=3.6
License-File: LICENSE.txt
